fluentcms_button/__init__.py
fluentcms_button/appsettings.py
fluentcms_button/content_plugins.py
fluentcms_button/models.py
fluentcms_button/tests.py
fluentcms_button/locale/nl/LC_MESSAGES/django.mo
fluentcms_button/locale/nl/LC_MESSAGES/django.po
fluentcms_button/migrations/0001_initial.py
fluentcms_button/migrations/0002_buttonitem_align.py
fluentcms_button/migrations/0003_remove_block.py
fluentcms_button/migrations/0004_remove_null.py
fluentcms_button/migrations/__init__.py
fluentcms_button/templates/fluentcms_button/button.html
fluentcms_button-3.0.dist-info/AUTHORS
fluentcms_button-3.0.dist-info/LICENSE
fluentcms_button-3.0.dist-info/METADATA
fluentcms_button-3.0.dist-info/WHEEL
fluentcms_button-3.0.dist-info/top_level.txt
fluentcms_button-3.0.dist-info/RECORD
