Metadata-Version: 2.1
Name: fluentcms-button
Version: 3.0
Summary: Bootstrap 3 Button element for django-fluent-contents
Home-page: https://github.com/edoburu/fluentcms-button
Author: Diederik van der Boor
Author-email: opensource@edoburu.nl
License: Apache 2.0
Download-URL: https://github.com/edoburu/fluentcms-button/zipball/master
Platform: UNKNOWN
Classifier: Development Status :: 5 - Production/Stable
Classifier: Environment :: Web Environment
Classifier: Framework :: Django
Classifier: Intended Audience :: Developers
Classifier: License :: OSI Approved :: Apache Software License
Classifier: Operating System :: OS Independent
Classifier: Programming Language :: Python
Classifier: Programming Language :: Python :: 2.7
Classifier: Programming Language :: Python :: 3
Classifier: Programming Language :: Python :: 3.4
Classifier: Programming Language :: Python :: 3.5
Classifier: Programming Language :: Python :: 3.6
Classifier: Framework :: Django
Classifier: Framework :: Django :: 1.10
Classifier: Framework :: Django :: 1.11
Classifier: Framework :: Django :: 2.0
Classifier: Topic :: Internet :: WWW/HTTP
Classifier: Topic :: Internet :: WWW/HTTP :: Dynamic Content
Classifier: Topic :: Software Development :: Libraries :: Python Modules
Requires: Django (>=1.10)
Requires-Dist: django-fluent-contents (>=2.0)
